{"allergies":["NKDA"],"date":"2020-02-11T15:48:03.000Z","apgar":{},"notes":{"family_history":"","prenatal_development":"","indication_for_referral":"DI + épilepsie","genetic_notes":"","medical_history":"Hyperplasie congénitale des surrénales, dx à 6 ans (puberté précoce)\r\nÉpilepsie, 1e épisode à 4 ans, possible encéphalite virale, mais pas d'agent infectieux identifié. Persistance épilepsie réfractaire depuis (1 crise/2sem), ss Frisium, Keppra, Trileptal.\r\nTDAH, dx vers 6 ans\r\nDéficience intellectuelle, dx à 7 ans. Actuellement en classe spéciale, niveau 1e année primaire.\r\nDéveloppement aurait été tout à fait normal jusqu'à 4 ans selon parents.\r\n\r\nIRM cérébrale 2006 & 2007: normal\r\nÉchographie abdominale 2009: normal\r\nÂge osseux 2008 (6 ans 6 mois): 13 ans 6 mois\r\nDensité osseuse 2011: normal","diagnosis_notes":""},"ethnicity":{"maternal_ethnicity":["Pérou"],"paternal_ethnicity":["El Salvador"]},"date_of_birth":{"month":5,"year":2002,"day":30},"global_mode_of_inheritance":[{"id":"HP:0003745","label":"Sporadic"},{"id":"HP:0000006","label":"Autosomal dominant inheritance"},{"id":"HP:0000007","label":"Autosomal recessive inheritance"}],"solved":{"status":"unsolved"},"external_id":"2082552","clinicalStatus":"affected","disorders":[],"features":[{"id":"HP:0012188","label":"Hyperemesis gravidarum","type":"prenatal_phenotype","observed":"no"},{"id":"HP:0008071","label":"Maternal hypertension","type":"prenatal_phenotype","observed":"no"},{"id":"HP:0009800","label":"Maternal diabetes","type":"prenatal_phenotype","observed":"no"},{"id":"HP:0030244","label":"Maternal fever in pregnancy","type":"prenatal_phenotype","observed":"no"},{"id":"HP:0100622","label":"Maternal seizures","type":"prenatal_phenotype","observed":"no"},{"id":"HP:0011438","label":"Maternal teratogenic exposure","type":"prenatal_phenotype","observed":"no"},{"id":"HP:0100603","label":"Toxemia of pregnancy","type":"prenatal_phenotype","observed":"no"},{"id":"HP:0011436","label":"Abnormal maternal serum screening","type":"prenatal_phenotype","observed":"no"},{"id":"HP:0001511","label":"Intrauterine growth retardation","type":"prenatal_phenotype","observed":"no"},{"id":"HP:0001562","label":"Oligohydramnios","type":"prenatal_phenotype","observed":"no"},{"id":"HP:0001561","label":"Polyhydramnios","type":"prenatal_phenotype","observed":"no"},{"id":"HP:0001558","label":"Decreased fetal movement","type":"prenatal_phenotype","observed":"no"},{"id":"HP:0010519","label":"Increased fetal movement","type":"prenatal_phenotype","observed":"no"},{"id":"HP:0001787","label":"Abnormal delivery","type":"prenatal_phenotype","observed":"no"},{"id":"HP:0001622","label":"Premature birth","type":"prenatal_phenotype","observed":"no"},{"id":"HP:0002643","label":"Neonatal respiratory distress","type":"prenatal_phenotype","observed":"no"},{"id":"HP:0006579","label":"Prolonged neonatal jaundice","type":"prenatal_phenotype","observed":"no"},{"id":"HP:0002033","label":"Poor suck","type":"prenatal_phenotype","observed":"no"},{"id":"HP:0001998","label":"Neonatal hypoglycemia","type":"prenatal_phenotype","observed":"no"},{"id":"HP:0040187","label":"Neonatal sepsis","type":"prenatal_phenotype","observed":"no"},{"id":"HP:0000280","label":"Coarse facial features","type":"phenotype","observed":"yes"},{"notes":"Dos","qualifiers":[{"id":"HP:0012838","label":"Localized","type":"spatial_pattern"}],"id":"HP:0009719","label":"Hypomelanotic macule","type":"phenotype","observed":"yes"},{"id":"HP:0010864","label":"Intellectual disability, severe","type":"phenotype","observed":"yes"},{"notes":"tonico-cloniques","id":"HP:0011169","label":"Generalized clonic seizures","type":"phenotype","observed":"yes"}],"contact":[{"name":"Guylaine D'Amours","id":"xwiki:XWiki.gadmours","email":"g.damours@umontreal.ca"}],"last_modification_date":"2020-02-11T16:08:43.000Z","patient_name":{"last_name":"Soto","first_name":"Christopher"},"specificity":{"date":"2021-03-08T19:01:53.320Z","score":0.9492329068007166,"server":"local-omim"},"nonstandard_features":[{"label":"clubbing","type":"phenotype","observed":"yes"}],"id":"P0000672","prenatal_perinatal_history":{"multipleGestation":false,"icsi":false,"maternal_age":0,"paternal_age":0,"ivf":false,"assistedReproduction_donoregg":false,"assistedReproduction_iui":false,"twinNumber":null,"assistedReproduction_fertilityMeds":false,"gestation":42,"assistedReproduction_surrogacy":false,"assistedReproduction_donorsperm":false},"family_history":{"miscarriages":false,"consanguinity":false,"affectedRelatives":false},"genes":[],"life_status":"alive","sex":"M","clinical-diagnosis":[],"reporter":"gadmours","last_modified_by":"gadmours","global_age_of_onset":[{"id":"HP:0003593","label":"Infantile onset"}],"report_id":"P0000672","meta":{"hgnc_version":"2017-07-18T13:03:51.594Z","omim_version":"2017-07-18T18:53:21.802Z","ordo_version":"2.3","hpo_version":"releases/2017-06-30","phenotips_version":"1.3.9-gene42"}}