{"allergies":["NKDA"],"date":"2020-01-18T01:02:47.000Z","apgar":{"apgar1":5,"apgar5":1},"notes":{"family_history":"Père avec difficultés d'apprentissage\r\nCousin paternel avec polydactylie post-axiale","prenatal_development":"Hypotonia at birth, apnea at 5 min of life\r\nPoor relfexes (grasp, succion, moro)\r\nAPGAR 5-1-8","indication_for_referral":"Macrocéphalie, hypotonie, retard moteur","genetic_notes":"","medical_history":"","diagnosis_notes":""},"ethnicity":{"maternal_ethnicity":["caucasienne"],"paternal_ethnicity":["caucasien "]},"date_of_birth":{"month":7,"year":2019,"day":8},"global_mode_of_inheritance":[{"id":"HP:0003745","label":"Sporadic"},{"id":"HP:0000006","label":"Autosomal dominant inheritance"},{"id":"HP:0000007","label":"Autosomal recessive inheritance"},{"id":"HP:0010985","label":"Gonosomal inheritance"},{"id":"HP:0001426","label":"Multifactorial inheritance"}],"solved":{"status":"unsolved"},"external_id":"3250200","clinicalStatus":"affected","disorders":[],"features":[{"id":"HP:0000028","label":"Cryptorchidism","type":"phenotype","observed":"no"},{"id":"HP:0000047","label":"Hypospadias","type":"phenotype","observed":"no"},{"id":"HP:0000062","label":"Ambiguous genitalia","type":"phenotype","observed":"no"},{"id":"HP:0000069","label":"Abnormality of the ureter","type":"phenotype","observed":"no"},{"id":"HP:0000085","label":"Horseshoe kidney","type":"phenotype","observed":"no"},{"id":"HP:0000098","label":"Tall stature","type":"phenotype","observed":"no"},{"id":"HP:0000107","label":"Renal cyst","type":"phenotype","observed":"no"},{"id":"HP:0000175","label":"Cleft palate","type":"phenotype","observed":"no"},{"id":"HP:0000204","label":"Cleft upper lip","type":"phenotype","observed":"no"},{"id":"HP:0000252","label":"Microcephaly","type":"phenotype","observed":"no"},{"id":"HP:0000356","label":"Abnormality of the outer ear","type":"phenotype","observed":"no"},{"id":"HP:0000359","label":"Abnormality of the inner ear","type":"phenotype","observed":"no"},{"id":"HP:0000384","label":"Preauricular skin tag","type":"phenotype","observed":"no"},{"id":"HP:0000405","label":"Conductive hearing impairment","type":"phenotype","observed":"no"},{"id":"HP:0000407","label":"Sensorineural hearing impairment","type":"phenotype","observed":"no"},{"id":"HP:0000479","label":"Abnormality of the retina","type":"phenotype","observed":"no"},{"id":"HP:0000481","label":"Abnormality of the cornea","type":"phenotype","observed":"no"},{"id":"HP:0000486","label":"Strabismus","type":"phenotype","observed":"no"},{"id":"HP:0000505","label":"Visual impairment","type":"phenotype","observed":"no"},{"id":"HP:0000518","label":"Cataract","type":"phenotype","observed":"no"},{"id":"HP:0000568","label":"Microphthalmia","type":"phenotype","observed":"no"},{"id":"HP:0000587","label":"Abnormality of the optic nerve","type":"phenotype","observed":"no"},{"id":"HP:0000589","label":"Coloboma","type":"phenotype","observed":"no"},{"id":"HP:0000593","label":"Abnormality of the anterior chamber","type":"phenotype","observed":"no"},{"id":"HP:0000601","label":"Hypotelorism","type":"phenotype","observed":"no"},{"id":"HP:0000639","label":"Nystagmus","type":"phenotype","observed":"no"},{"id":"HP:0000776","label":"Congenital diaphragmatic hernia","type":"phenotype","observed":"no"},{"id":"HP:0000795","label":"Abnormality of the urethra","type":"phenotype","observed":"no"},{"id":"HP:0000819","label":"Diabetes mellitus","type":"phenotype","observed":"no"},{"id":"HP:0000925","label":"Abnormality of the vertebral column","type":"phenotype","observed":"no"},{"id":"HP:0000953","label":"Hyperpigmentation of the skin","type":"phenotype","observed":"no"},{"id":"HP:0001180","label":"Hand oligodactyly","type":"phenotype","observed":"no"},{"id":"HP:0001263","label":"Global developmental delay","type":"phenotype","observed":"no"},{"id":"HP:0001363","label":"Craniosynostosis","type":"phenotype","observed":"no"},{"id":"HP:0001371","label":"Flexion contracture","type":"phenotype","observed":"no"},{"id":"HP:0001396","label":"Cholestasis","type":"phenotype","observed":"no"},{"id":"HP:0001508","label":"Failure to thrive","type":"phenotype","observed":"no"},{"id":"HP:0001528","label":"Hemihypertrophy","type":"phenotype","observed":"no"},{"id":"HP:0001539","label":"Omphalocele","type":"phenotype","observed":"no"},{"id":"HP:0001543","label":"Gastroschisis","type":"phenotype","observed":"no"},{"id":"HP:0001629","label":"Ventricular septal defect","type":"phenotype","observed":"no"},{"id":"HP:0001631","label":"Atrial septal defect","type":"phenotype","observed":"no"},{"id":"HP:0001636","label":"Tetralogy of Fallot","type":"phenotype","observed":"no"},{"id":"HP:0001638","label":"Cardiomyopathy","type":"phenotype","observed":"no"},{"id":"HP:0001674","label":"Complete atrioventricular canal defect","type":"phenotype","observed":"no"},{"id":"HP:0001680","label":"Coarctation of aorta","type":"phenotype","observed":"no"},{"id":"HP:0001738","label":"Exocrine pancreatic insufficiency","type":"phenotype","observed":"no"},{"id":"HP:0001762","label":"Talipes equinovarus","type":"phenotype","observed":"no"},{"id":"HP:0001770","label":"Toe syndactyly","type":"phenotype","observed":"no"},{"id":"HP:0001836","label":"Camptodactyly of toe","type":"phenotype","observed":"no"},{"id":"HP:0001849","label":"Foot oligodactyly","type":"phenotype","observed":"no"},{"id":"HP:0001999","label":"Abnormal facial shape","type":"phenotype","observed":"no"},{"id":"HP:0002032","label":"Esophageal atresia","type":"phenotype","observed":"no"},{"id":"HP:0002088","label":"Abnormality of lung morphology","type":"phenotype","observed":"no"},{"id":"HP:0002251","label":"Aganglionic megacolon","type":"phenotype","observed":"no"},{"id":"HP:0002575","label":"Tracheoesophageal fistula","type":"phenotype","observed":"no"},{"id":"HP:0002650","label":"Scoliosis","type":"phenotype","observed":"no"},{"id":"HP:0002652","label":"Skeletal dysplasia","type":"phenotype","observed":"no"},{"id":"HP:0002659","label":"Increased susceptibility to fractures","type":"phenotype","observed":"no"},{"id":"HP:0002910","label":"Elevated hepatic transaminases","type":"phenotype","observed":"no"},{"id":"HP:0004322","label":"Short stature","type":"phenotype","observed":"no"},{"id":"HP:0004324","label":"Increased body weight","type":"phenotype","observed":"no"},{"id":"HP:0004325","label":"Decreased body weight","type":"phenotype","observed":"no"},{"id":"HP:0004467","label":"Preauricular pit","type":"phenotype","observed":"no"},{"id":"HP:0005306","label":"Capillary hemangiomas","type":"phenotype","observed":"no"},{"id":"HP:0006101","label":"Finger syndactyly","type":"phenotype","observed":"no"},{"id":"HP:0009816","label":"Lower limb undergrowth","type":"phenotype","observed":"no"},{"id":"HP:0009824","label":"Upper limb undergrowth","type":"phenotype","observed":"no"},{"id":"HP:0010862","label":"Delayed fine motor development","type":"phenotype","observed":"no"},{"id":"HP:0011276","label":"Vascular skin abnormality","type":"phenotype","observed":"no"},{"id":"HP:0011675","label":"Arrhythmia","type":"phenotype","observed":"no"},{"id":"HP:0100258","label":"Preaxial polydactyly","type":"phenotype","observed":"no"},{"id":"HP:0100259","label":"Postaxial polydactyly","type":"phenotype","observed":"no"},{"id":"HP:0100490","label":"Camptodactyly of finger","type":"phenotype","observed":"no"},{"id":"HP:0012188","label":"Hyperemesis gravidarum","type":"prenatal_phenotype","observed":"no"},{"id":"HP:0008071","label":"Maternal hypertension","type":"prenatal_phenotype","observed":"no"},{"id":"HP:0009800","label":"Maternal diabetes","type":"prenatal_phenotype","observed":"no"},{"id":"HP:0030244","label":"Maternal fever in pregnancy","type":"prenatal_phenotype","observed":"no"},{"id":"HP:0100622","label":"Maternal seizures","type":"prenatal_phenotype","observed":"no"},{"id":"HP:0011438","label":"Maternal teratogenic exposure","type":"prenatal_phenotype","observed":"no"},{"id":"HP:0100603","label":"Toxemia of pregnancy","type":"prenatal_phenotype","observed":"no"},{"id":"HP:0011436","label":"Abnormal maternal serum screening","type":"prenatal_phenotype","observed":"no"},{"id":"HP:0001511","label":"Intrauterine growth retardation","type":"prenatal_phenotype","observed":"no"},{"id":"HP:0001562","label":"Oligohydramnios","type":"prenatal_phenotype","observed":"no"},{"id":"HP:0001561","label":"Polyhydramnios","type":"prenatal_phenotype","observed":"no"},{"id":"HP:0001558","label":"Decreased fetal movement","type":"prenatal_phenotype","observed":"no"},{"id":"HP:0010519","label":"Increased fetal movement","type":"prenatal_phenotype","observed":"no"},{"id":"HP:0001787","label":"Abnormal delivery","type":"prenatal_phenotype","observed":"no"},{"id":"HP:0001622","label":"Premature birth","type":"prenatal_phenotype","observed":"no"},{"id":"HP:0001518","label":"Small for gestational age","type":"prenatal_phenotype","observed":"no"},{"id":"HP:0001520","label":"Large for gestational age","type":"prenatal_phenotype","observed":"no"},{"id":"HP:0003517","label":"Birth length greater than 97th percentile","type":"prenatal_phenotype","observed":"no"},{"id":"HP:0006579","label":"Prolonged neonatal jaundice","type":"prenatal_phenotype","observed":"no"},{"id":"HP:0001998","label":"Neonatal hypoglycemia","type":"prenatal_phenotype","observed":"no"},{"id":"HP:0040187","label":"Neonatal sepsis","type":"prenatal_phenotype","observed":"no"},{"id":"HP:0004875","label":"Neonatal inspiratory stridor","type":"prenatal_phenotype","observed":"no"},{"id":"HP:0000256","label":"Macrocephaly","type":"phenotype","observed":"yes"},{"id":"HP:0000316","label":"Hypertelorism","type":"phenotype","observed":"yes"},{"notes":"Petite tache hyperpigmentée au dos à gauche 0,75 x 0,3 cm","id":"HP:0001010","label":"Hypopigmentation of the skin","type":"phenotype","observed":"yes"},{"id":"HP:0002020","label":"Gastroesophageal reflux","type":"phenotype","observed":"yes"},{"id":"HP:0002194","label":"Delayed gross motor development","type":"phenotype","observed":"yes"},{"id":"HP:0004488","label":"Macrocephaly at birth","type":"phenotype","observed":"yes"},{"id":"HP:0025336","label":"Delayed ability to sit","type":"phenotype","observed":"yes"},{"id":"HP:0002033","label":"Poor suck","type":"prenatal_phenotype","observed":"yes"},{"id":"HP:0002643","label":"Neonatal respiratory distress","type":"prenatal_phenotype","observed":"yes"},{"id":"HP:0004488","label":"Macrocephaly at birth","type":"prenatal_phenotype","observed":"yes"},{"id":"HP:0012768","label":"Neonatal asphyxia","type":"prenatal_phenotype","observed":"yes"}],"contact":[{"name":"England Jade","id":"xwiki:XWiki.ejade","email":"jade.england@umontreal.ca"}],"last_modification_date":"2020-01-20T23:51:55.000Z","patient_name":{"last_name":"Lalonde","first_name":"Mavrik"},"specificity":{"date":"2021-03-08T19:01:52.937Z","score":0.9841578526346424,"server":"local-omim"},"nonstandard_features":[{"label":"Downslanting palpebral fissures","categories":[{"id":"HP:0000478","label":"Abnormality of the eye"}],"type":"phenotype","observed":"yes"},{"label":"Flat nasal bridge","categories":[{"id":"HP:0000478","label":"Abnormality of the eye"}],"type":"phenotype","observed":"yes"},{"label":"Hyperpigmentation","type":"phenotype","observed":"yes"},{"label":"Hypotonie","categories":[{"id":"HP:0011446","label":"Abnormality of higher mental function"}],"type":"phenotype","observed":"yes"},{"label":"Premiers orteils larges","categories":[{"id":"HP:0000924","label":"Abnormality of the skeletal system"},{"id":"HP:0003011","label":"Abnormality of the musculature"},{"id":"HP:0040064","label":"Abnormality of limbs"}],"type":"phenotype","observed":"yes"},{"notes":"Sous gavages ad 1 mois et demi de vie\r\nDifficulté aux boires","qualifiers":[{"id":"HP:0003623","label":"Neonatal onset","type":"age_of_onset"}],"label":"Troubles alimentations ","categories":[{"id":"HP:0011024","label":"Abnormality of the gastrointestinal tract"}],"type":"phenotype","observed":"yes"},{"label":"Head circumference between 90-97th percentile","categories":[{"id":"HP:0001507","label":"Growth abnormality"},{"id":"HP:0000240","label":"Abnormality of skull size"}],"type":"prenatal_phenotype","observed":"yes"}],"id":"P0000665","prenatal_perinatal_history":{"multipleGestation":false,"icsi":false,"maternal_age":0,"paternal_age":0,"ivf":false,"assistedReproduction_donoregg":false,"assistedReproduction_iui":false,"twinNumber":null,"assistedReproduction_fertilityMeds":false,"gestation":40,"assistedReproduction_surrogacy":false,"assistedReproduction_donorsperm":false},"family_history":{"miscarriages":false,"consanguinity":false,"affectedRelatives":false},"genes":[],"life_status":"alive","sex":"M","clinical-diagnosis":[],"reporter":"ejade","last_modified_by":"ejade","global_age_of_onset":[{"id":"HP:0003623","label":"Neonatal onset"}],"report_id":"P0000665","meta":{"hgnc_version":"2017-07-18T13:03:51.594Z","omim_version":"2017-07-18T18:53:21.802Z","ordo_version":"2.3","hpo_version":"releases/2017-06-30","phenotips_version":"1.3.9-gene42"}}